nonebot_plugin_batitle-0.1.6.dist-info/METADATA
nonebot_plugin_batitle-0.1.6.dist-info/WHEEL
nonebot_plugin_batitle-0.1.6.dist-info/licenses/LICENSE
nonebot_plugin_batitle/__init__.py
nonebot_plugin_batitle/draw.py
nonebot_plugin_batitle/src/Merged.otf
nonebot_plugin_batitle/src/cross.png
nonebot_plugin_batitle/src/halo.png
nonebot_plugin_batitle-0.1.6.dist-info/RECORD
