Metadata-Version: 2.1
Name: nonebot-plugin-batitle
Version: 0.1.6
Summary: BlueArchive Title Generator
Home-page: https://github.com/MerCuJerry/nonebot-plugin-batitle
Author-Email: MerCuJerry <mercujerry@gmail.com>
License: MIT License
Project-URL: Homepage, https://github.com/MerCuJerry/nonebot-plugin-batitle
Requires-Python: <4.0,>=3.8
Requires-Dist: nonebot2>=2.1.0
Requires-Dist: nonebot-plugin-send-anything-anywhere>=0.3.2
Requires-Dist: pillow<11.0.0,>=9.2.0
